pinkman/__init__.py
pinkman/cli.py
pinkman/command/__init__.py
pinkman/command/server.py
pinkman/command/worker.py
pinkman/exception/__init__.py
pinkman/model/__init__.py
pinkman/model/message.py
pinkman/model/remote.py
pinkman/module/__init__.py
pinkman/module/backend.py
pinkman/module/config.py
pinkman/module/database.py
pinkman/module/file.py
pinkman/module/mailbox.py
pinkman-0.1.7.dist-info/LICENSE.txt
pinkman-0.1.7.dist-info/METADATA
pinkman-0.1.7.dist-info/WHEEL
pinkman-0.1.7.dist-info/entry_points.txt
pinkman-0.1.7.dist-info/top_level.txt
pinkman-0.1.7.dist-info/RECORD
