Metadata-Version: 2.1
Name: pinkman
Version: 0.1.7
Summary: An SMTP Server to forward Messages into A Backend System.
Home-page: https://github.com/Clivern/Pinkman/
Author: Clivern
Author-email: hello@clivern.com
License: MIT
Project-URL: Documentation, https://github.com/Clivern/Pinkman/
Project-URL: Source, https://github.com/Clivern/Pinkman/
Project-URL: Changelog, https://github.com/Clivern/Pinkman/blob/main/CHANGELOG.rst
Project-URL: Tracker, https://github.com/Clivern/Pinkman/issues
Project-URL: Download, https://pypi.org/project/Pinkman/#files
Platform: any
Classifier: Development Status :: 5 - Production/Stable
Classifier: Programming Language :: Python
Classifier: License :: OSI Approved :: MIT License
License-File: LICENSE.txt
Requires-Dist: click<=8.1.7
Requires-Dist: PyYAML<=6.0.2
Requires-Dist: requests<=2.32.3
Requires-Dist: importlib-metadata<=8.4.0; python_version < "3.8"
